tesla_ce_client/__init__.py
tesla_ce_client/client.py
tesla_ce_client/connector.py
tesla_ce_client/exception.py
tesla_ce_client/data/VERSION
tesla_ce_client/institution/__init__.py
tesla_ce_client/provider/__init__.py
tesla_ce_client/provider/client.py
tesla_ce_client/provider/enrolment.py
tesla_ce_client/provider/notification.py
tesla_ce_client/provider/verification.py
tesla_ce_client/v1/__init__.py
tesla_ce_client/v1/api.py
tesla_ce_client/v1/rt.py
tesla_ce_client/v1/tep.py
tesla_ce_client/v1/tip.py
tesla_ce_client/v1/v1.py
tesla_ce_client/vle/__init__.py
tesla_ce_client/vle/client.py
tesla_ce_client/vle/course/__init__.py
tesla_ce_client/vle/course/client.py
tesla_ce_client/vle/course/activity/__init__.py
tesla_ce_client/vle/course/activity/client.py
tesla_ce_client/vle/course/activity/results/__init__.py
tesla_ce_client/vle/course/activity/results/client.py
tesla_ce_client/vle/course/learner/__init__.py
tesla_ce_client/vle/course/learner/client.py
tests/__init__.py
tests/learners/__init__.py
tests/learners/test_client.py
tesla_ce_client-0.0.4.dist-info/LICENSE
tesla_ce_client-0.0.4.dist-info/METADATA
tesla_ce_client-0.0.4.dist-info/WHEEL
tesla_ce_client-0.0.4.dist-info/top_level.txt
tesla_ce_client-0.0.4.dist-info/RECORD
