Metadata-Version: 2.1
Name: tesla-ce-client
Version: 0.0.4
Summary: TeSLA CE Client for Python
Home-page: https://tesla-ce.github.io
Author: Xavier Baro
Author-email: xbaro@uoc.edu
License: UNKNOWN
Project-URL: Documentation, https://tesla-ce.github.io/python-client/
Project-URL: Source, https://github.com/tesla-ce/python-client
Platform: UNKNOWN
Classifier: Programming Language :: Python :: 3
Classifier: License :: OSI Approved :: GNU Affero General Public License v3 or later (AGPLv3+)
Classifier: Operating System :: POSIX :: Linux
Requires-Python: >=3.6
License-File: LICENSE
Requires-Dist: deprecation
Requires-Dist: requests
Requires-Dist: sentry-sdk
Requires-Dist: simplejson
